{"type": "FeatureCollection", "features": [{"type": "Feature", "geometry": {"type": "Point", "coordinates": [79.0568778886292, 21.129552500057073]}, "properties": {"title": "Prediction0", "icon": "monument"}}, {"type": "Feature", "geometry": {"type": "Point", "coordinates": [79.05670472414772, 21.12944330573087]}, "properties": {"title": "Prediction1", "icon": "monument"}}, {"type": "Feature", "geometry": {"type": "Point", "coordinates": [79.05691582893888, 21.129280951324684]}, "properties": {"title": "Prediction2", "icon": "monument"}}]}