{"type": "FeatureCollection", "features": [{"type": "Feature", "geometry": {"type": "Point", "coordinates": [79.05666623995765, 21.129318763752337]}, "properties": {"title": "Prediction0", "icon": "monument"}}]}