{"type": "FeatureCollection", "features": [{"type": "Feature", "geometry": {"type": "Point", "coordinates": [79.05710641632854, 21.12981650029284]}, "properties": {"title": "Prediction0", "icon": "monument"}}, {"type": "Feature", "geometry": {"type": "Point", "coordinates": [79.0566129996759, 21.129213400091608]}, "properties": {"title": "Prediction1", "icon": "monument"}}, {"type": "Feature", "geometry": {"type": "Point", "coordinates": [79.05676377265293, 21.129651727194155]}, "properties": {"title": "Prediction2", "icon": "monument"}}]}