{"type": "FeatureCollection", "features": [{"type": "Feature", "geometry": {"type": "Point", "coordinates": [79.05684972695569, 21.129367681483522]}, "properties": {"title": "Prediction0", "icon": "monument"}}, {"type": "Feature", "geometry": {"type": "Point", "coordinates": [79.05678294106274, 21.129430529096965]}, "properties": {"title": "Prediction1", "icon": "monument"}}, {"type": "Feature", "geometry": {"type": "Point", "coordinates": [79.05676350027933, 21.129701000310458]}, "properties": {"title": "Prediction2", "icon": "monument"}}, {"type": "Feature", "geometry": {"type": "Point", "coordinates": [79.05659370345381, 21.129417622356513]}, "properties": {"title": "Prediction3", "icon": "monument"}}, {"type": "Feature", "geometry": {"type": "Point", "coordinates": [79.05690338432296, 21.129511384307396]}, "properties": {"title": "Prediction4", "icon": "monument"}}, {"type": "Feature", "geometry": {"type": "Point", "coordinates": [79.05676516632052, 21.12954383364504]}, "properties": {"title": "Prediction5", "icon": "monument"}}]}