{"type": "FeatureCollection", "features": [{"type": "Feature", "geometry": {"type": "Point", "coordinates": [79.05703606635943, 21.12974973360765]}, "properties": {"title": "Prediction0", "icon": "monument"}}, {"type": "Feature", "geometry": {"type": "Point", "coordinates": [79.0567260001288, 21.129115000107376]}, "properties": {"title": "Prediction1", "icon": "monument"}}, {"type": "Feature", "geometry": {"type": "Point", "coordinates": [79.05678254518197, 21.1296534546529]}, "properties": {"title": "Prediction2", "icon": "monument"}}, {"type": "Feature", "geometry": {"type": "Point", "coordinates": [79.05665500023908, 21.12919700009325]}, "properties": {"title": "Prediction3", "icon": "monument"}}, {"type": "Feature", "geometry": {"type": "Point", "coordinates": [79.05680399990189, 21.129619999651894]}, "properties": {"title": "Prediction4", "icon": "monument"}}]}