{"type": "FeatureCollection", "features": [{"type": "Feature", "geometry": {"type": "Point", "coordinates": [79.05673699996265, 21.12963216630646]}, "properties": {"title": "Prediction0", "icon": "monument"}}, {"type": "Feature", "geometry": {"type": "Point", "coordinates": [79.05653422235416, 21.129288222151807]}, "properties": {"title": "Prediction1", "icon": "monument"}}, {"type": "Feature", "geometry": {"type": "Point", "coordinates": [79.0569353076548, 21.129725231029834]}, "properties": {"title": "Prediction2", "icon": "monument"}}, {"type": "Feature", "geometry": {"type": "Point", "coordinates": [79.0566280669859, 21.129609999713026]}, "properties": {"title": "Prediction3", "icon": "monument"}}]}